Metadata-Version: 2.1
Name: mtag-tool
Version: 1.0.0
Summary: MP3 tag编辑器，支持从网易云补全歌曲信息.
Home-page: https://github.com/wang0618/mtag_tool
Author: WangWeimin
Author-email: wang0.618@qq.com
License: MIT
Project-URL: Source, https://github.com/wang0618/mtag_tool
Platform: UNKNOWN
Classifier: Programming Language :: Python :: 3
Classifier: Programming Language :: Python :: 3.5
Classifier: Programming Language :: Python :: 3.6
Classifier: Programming Language :: Python :: 3.7
Classifier: Programming Language :: Python :: 3.8
Requires-Python: >=3.5.2
